market_calendar_tool/__init__.py
market_calendar_tool/api.py
market_calendar_tool/cleaning/__init__.py
market_calendar_tool/cleaning/cleaner.py
market_calendar_tool/mixins/__init__.py
market_calendar_tool/mixins/save_mixin.py
market_calendar_tool/scraper/__init__.py
market_calendar_tool/scraper/base_scraper.py
market_calendar_tool/scraper/data_processor.py
market_calendar_tool/scraper/extended_scraper.py
market_calendar_tool/scraper/models.py
market_calendar_tool-0.2.1.dist-info/LICENSE
market_calendar_tool-0.2.1.dist-info/METADATA
market_calendar_tool-0.2.1.dist-info/WHEEL
market_calendar_tool-0.2.1.dist-info/RECORD
