Metadata-Version: 2.1
Name: market-calendar-tool
Version: 0.2.1
Summary: Market Calendar Tool is a Python package that scrapes economic calendar data from multiple financial websites and returns it as pandas DataFrames for easy analysis.
License: MIT
Author: Pavel Krusek
Author-email: pavel@krusek.dk
Requires-Python: >=3.12,<4.0
Classifier: License :: OSI Approved :: MIT License
Classifier: Programming Language :: Python :: 3
Classifier: Programming Language :: Python :: 3.12
Classifier: Programming Language :: Python :: 3.13
Requires-Dist: aiohttp (>=3.10.10,<4.0.0)
Requires-Dist: asyncio (>=3.4.3,<4.0.0)
Requires-Dist: beautifulsoup4 (>=4.12.3,<5.0.0)
Requires-Dist: loguru (>=0.7.2,<0.8.0)
Requires-Dist: pandas (>=2.2.3,<3.0.0)
Requires-Dist: pyarrow (>=17.0.0,<18.0.0)
Requires-Dist: pycountry (>=24.6.1,<25.0.0)
Requires-Dist: requests (>=2.32.3,<3.0.0)
